mdplus/__init__.py
mdplus/_version.py
mdplus/cli.py
mdplus/cli_old.py
mdplus/config.py
mdplus/core_old.py
mdplus/logger.py
mdplus/core/__init__.py
mdplus/core/generator.py
mdplus/core/importer.py
mdplus/core/documents/block.py
mdplus/core/documents/definitions.py
mdplus/core/documents/document.py
mdplus/core/documents/structure.py
mdplus/core/environments/base.py
mdplus/core/environments/ros2.py
mdplus/generators/__init__.py
mdplus/generators/flags.py
mdplus/generators/generate/__init__.py
mdplus/generators/generate/content.py
mdplus/generators/generate/installation.py
mdplus/generators/generate/getting_started/__init__.py
mdplus/generators/generate/getting_started/pakk.py
mdplus/generators/include/__init__.py
mdplus/generators/include/example.py
mdplus/generators/include/examples.py
mdplus/generators/include/md.py
mdplus/generators/ros/__init__.py
mdplus/generators/ros/interfaces.py
mdplus/generators/ros/launchs.py
mdplus/generators/ros/nodes.py
mdplus/templates/Hooks.md
mdplus/templates/MDP_IGNORE
mdplus/templates/__init__.py
mdplus/templates/default/DOCS.md
mdplus/templates/default/README.md
mdplus/templates/init/_README.md
mdplus/templates/init/__init__.py
mdplus/templates/init/docs/AUTHORS.md
mdplus/templates/init/docs/__init__.py
mdplus/templates/init/examples/__init__.py
mdplus/templates/init/examples/example1.py
mdplus/templates/init/examples/mdplus.json
mdplus/util/__init__.py
mdplus/util/file_utils.py
mdplus/util/hooks.py
mdplus/util/markdown.py
mdplus/util/regex.py
mdplus/util/parser/__init__.py
mdplus/util/parser/py_parser.py
mdplus/util/parser/ros2_parser.py
markdown_plus-0.1.4.dist-info/METADATA
markdown_plus-0.1.4.dist-info/WHEEL
markdown_plus-0.1.4.dist-info/entry_points.txt
markdown_plus-0.1.4.dist-info/licenses/LICENSE
markdown_plus-0.1.4.dist-info/RECORD
