Metadata-Version: 2.3
Name: markdown-plus
Version: 0.1.4
Summary: Generator for markdown files.
Project-URL: Homepage, https://github.com/iCampus-Wildau/markdown-plus
Project-URL: Issues, https://github.com/iCampus-Wildau/markdown-plus/issues
Author-email: Valentin Schröter <vasc9380@th-wildau.de>
License-File: LICENSE
Classifier: Programming Language :: Python :: 3
Requires-Python: >=3.8
Requires-Dist: click
Requires-Dist: click-aliases
Requires-Dist: gitpython
Requires-Dist: inquirerpy
Requires-Dist: mistletoe
Requires-Dist: overrides
Requires-Dist: pandas
Requires-Dist: py-markdown-table
Requires-Dist: rich
